<?xml version="1.0" encoding="UTF-8"?>
<PublicationDelivery xmlns="http://www.netex.org.uk/netex" version="1.11:NO-NeTEx-fares:0.9">
  <!--

    IMPORTANT
    =========

    The master for this XML file is in the AtB-AS repository here:
    https://github.com/AtB-AS/netex-data/blob/main/vkt_school_product_and_details.xml

  -->
  <PublicationTimestamp>2020-09-01T12:00:00</PublicationTimestamp>
  <ParticipantRef>ABT-REFERENCEDATA</ParticipantRef>
  <dataObjects>

    <!-- ######## 2026/2027 ######## -->

    <!-- Vestfold fylke 2026-2027 (default) -->
    <ServiceCalendarFrame version="1" id="VKT:ServiceCalendarFrame:SchoolDayVKT2026-2027">
      <Name lang="eng">School year calendar for Vestfold</Name>
      <ServiceCalendar id="VKT:ServiceCalendar:SchoolDayVKT2026-2027" version="1">
        <dayTypes>
          <FareDayType version="1" id="VKT:FareDayType:SchoolDayVKT2026-2027">
            <properties>
              <PropertyOfDay>
                <HolidayTypes>SchoolDay</HolidayTypes>
              </PropertyOfDay>
            </properties>
          </FareDayType>
        </dayTypes>
        <operatingPeriods>
          <UicOperatingPeriod version="1" id="VKT:UicOperatingPeriod:SchoolDayVKT2026-2027">
            <FromDate>2026-08-17T00:00:00</FromDate>
            <ToDate>2027-06-20T23:59:59</ToDate>
            <ValidDayBits>
              1111100 <!-- Week 34 - School starts 17 August -->
              1111100 <!-- Week 35 -->
              1111100 <!-- Week 36 -->
              1111100 <!-- Week 37 -->
              1111100 <!-- Week 38 -->
              1111100 <!-- Week 39 -->
              1111100 <!-- Week 40 -->
              0000000 <!-- Week 41 - Autumn vacation -->
              1111100 <!-- Week 42 -->
              1111100 <!-- Week 43 -->
              1111100 <!-- Week 44 -->
              1111100 <!-- Week 45 -->
              1111100 <!-- Week 46 -->
              1111100 <!-- Week 47 -->
              1111100 <!-- Week 48 -->
              1111100 <!-- Week 49 -->
              1111100 <!-- Week 50 -->
              1111100 <!-- Week 51 -->
              0000000 <!-- Week 52 - Christmas vacation -->
              0000000 <!-- Week 53 - Christmas vacation -->
              0111100 <!-- Week 1 - Christmas vacation - school resumes 5 January -->
              1111100 <!-- Week 2 -->
              1111100 <!-- Week 3 -->
              1111100 <!-- Week 4 -->
              1111100 <!-- Week 5 -->
              1111100 <!-- Week 6 -->
              1111100 <!-- Week 7 -->
              0000000 <!-- Week 8 - Winter vacation -->
              1111100 <!-- Week 9 -->
              1111100 <!-- Week 10 -->
              1111100 <!-- Week 11 -->
              0000000 <!-- Week 12 - Easter -->
              0111100 <!-- Week 13 - Easter Monday -->
              1111100 <!-- Week 14 -->
              1111100 <!-- Week 15 -->
              1111100 <!-- Week 16 -->
              1111100 <!-- Week 17 -->
              1110000 <!-- Week 18 - Ascension + day off 7 May -->
              1111100 <!-- Week 19 -->
              0111100 <!-- Week 20 - May 17th -->
              1111100 <!-- Week 21 -->
              1111100 <!-- Week 22 -->
              1111100 <!-- Week 23 -->
              1111100 <!-- Week 24 - Last school day 18 June -->
            </ValidDayBits>
          </UicOperatingPeriod>
        </operatingPeriods>
        <dayTypeAssignments>
          <DayTypeAssignment version="1" id="VKT:DayTypeAssignment:SchoolDayVKT2026-2027" order="1">
            <OperatingPeriodRef ref="VKT:UicOperatingPeriod:SchoolDayVKT2026-2027"/>
            <DayTypeRef version="1" ref="VKT:FareDayType:SchoolDayVKT2026-2027"/>
          </DayTypeAssignment>
        </dayTypeAssignments>
      </ServiceCalendar>
    </ServiceCalendarFrame>
  </dataObjects>
</PublicationDelivery>
